[
    {
        "additional_info": "",
        "company_name": "JB Hi Fi Group Pty Ltd",
        "is_new": true,
        "job_date": null,
        "job_description": "Be part of Australia\u2019s fastest growing and largest consumer electronics retailing group - over 300 stores and 13,000 employees. Melbourne CBD + WFH",
        "job_title": "Senior Software Engineer",
        "job_url": "https://www.seek.com.au/job/73005433?type=promoted&ref=search-standalone",
        "location": "Melbourne VIC",
        "salary": "Competitive salary, great staff discounts & more!"
    },
    {
        "additional_info": "",
        "company_name": "Connect Recruitment",
        "is_new": true,
        "job_date": null,
        "job_description": "On the hunt for 3 amazing C++ Software Engineers to build exciting careers with one of the most sort after tech companies in Brissy! Grads welcome!",
        "job_title": "Software Engineer - C++ Image Processing",
        "job_url": "https://www.seek.com.au/job/72966075?type=promoted&ref=search-standalone",
        "location": "Brisbane QLD",
        "salary": null
    },
    {
        "additional_info": "",
        "company_name": "Vitil",
        "is_new": true,
        "job_date": "1h ago",
        "job_description": "Are you looking for a challenge, to be a part of a growing team, solving complex technical problems, then join our growing team at CredEntry.",
        "job_title": "Principal Software Engineer",
        "job_url": "https://www.seek.com.au/job/73026630?type=standout&ref=search-standalone",
        "location": "Perth WA",
        "salary": "$120,000 \u2013 $140,000 per year"
    },
    {
        "additional_info": "",
        "company_name": "FIRESOFT People",
        "is_new": true,
        "job_date": "1h ago",
        "job_description": "C/C++ Security Engineer",
        "job_title": "Security Reverse Engineer (C++/Vulnerability Research)",
        "job_url": "https://www.seek.com.au/job/73026590?type=standout&ref=search-standalone",
        "location": "Sydney NSW",
        "salary": null
    },
    {
        "additional_info": "",
        "company_name": "www.bustle.com.au",
        "is_new": true,
        "job_date": "4h ago",
        "job_description": "Backend Developer with a strategic focus on integrations to join a growing Perth SaaS business.",
        "job_title": "Backend Developer - Integrations",
        "job_url": "https://www.seek.com.au/job/73022545?type=standard&ref=search-standalone",
        "location": "Perth WA",
        "salary": "$110,000 \u2013 $130,000 per year"
    },
    {
        "additional_info": "",
        "company_name": "Professional Search Group",
        "is_new": true,
        "job_date": "4h ago",
        "job_description": "New opportunity for skilled iOS Developer based in Perth's CBD! Permanent opportunity with highly skilled team!",
        "job_title": "iOS Developer",
        "job_url": "https://www.seek.com.au/job/73022236?type=standard&ref=search-standalone",
        "location": "Perth WA",
        "salary": "AUD 130000 - 150000 per annum"
    },
    {
        "additional_info": "",
        "company_name": "Talent Locker",
        "is_new": true,
        "job_date": "4h ago",
        "job_description": "Responsible for development efforts for software enhancements, extensions, defect corrections and integration of features\nin Dynamics 365 F&O",
        "job_title": "MS Dynamics Technical Consultant",
        "job_url": "https://www.seek.com.au/job/73021558?type=standout&ref=search-standalone",
        "location": "Macquarie Park",
        "salary": "Solid day rate and flexible working available"
    },
    {
        "additional_info": "",
        "company_name": "Australian Finance Group",
        "is_new": true,
        "job_date": "5h ago",
        "job_description": "This role is perfect for a proactive and motivated individual to progress their career in a professional dynamic team environment.",
        "job_title": "Senior Software Developer",
        "job_url": "https://www.seek.com.au/job/72334542?type=standout&ref=search-standalone",
        "location": "West Perth",
        "salary": null
    },
    {
        "additional_info": "",
        "company_name": "Phillip Riley",
        "is_new": true,
        "job_date": "5h ago",
        "job_description": "Phillip Riley has partnered with an innovative Battery Storage business, with the capabilities to provide end to end solutions for its customers.",
        "job_title": "Senior Embedded Software Engineer",
        "job_url": "https://www.seek.com.au/job/73020742?type=standout&ref=search-standalone",
        "location": "Brisbane QLD",
        "salary": null
    },
    {
        "additional_info": "",
        "company_name": "Commonwealth Bank",
        "is_new": true,
        "job_date": "5h ago",
        "job_description": "As a Senior DevOps & Cloud Engineer, you will be a part of a Platform Engineering team that enables Cloud migration and Delivery pipeline for the D...",
        "job_title": "Senior Systems Engineer / Snr Devops Engineer (Kubernetes/EKS)",
        "job_url": "https://www.seek.com.au/job/73026846?type=standard&ref=search-standalone",
        "location": "Eveleigh",
        "salary": null
    },
    {
        "additional_info": "",
        "company_name": "Vectiq Pty Ltd",
        "is_new": true,
        "job_date": "5h ago",
        "job_description": "Senior Java Developer role with a large Federal Government Department in Canberra. Flexible work arrangements.",
        "job_title": "Java Developer",
        "job_url": "https://www.seek.com.au/job/73020562?type=standout&ref=search-standalone",
        "location": "Canberra ACT",
        "salary": null
    },
    {
        "additional_info": "",
        "company_name": "Talent \u2013 Specialists in tech, transformation & beyond",
        "is_new": true,
        "job_date": "5h ago",
        "job_description": "Talent International is searching for 7x Java Developer to join one of our Federal Government Clients who are expanding their team in Brisbane.",
        "job_title": "Java Developer",
        "job_url": "https://www.seek.com.au/job/73020447?type=standout&ref=search-standalone",
        "location": "North Lakes",
        "salary": "Market Rates"
    },
    {
        "additional_info": "",
        "company_name": "Clarrow Pty Ltd",
        "is_new": true,
        "job_date": "5h ago",
        "job_description": "Are you an ambitious Python Software Engineer who has a background in Java and looking to progress your career?",
        "job_title": "Python Engineer  ( Data ) Captial Markets",
        "job_url": "https://www.seek.com.au/job/73020151?type=standard&ref=search-standalone",
        "location": "Melbourne VIC",
        "salary": null
    },
    {
        "additional_info": "",
        "company_name": "Talent \u2013 Specialists in tech, transformation & beyond",
        "is_new": true,
        "job_date": "5h ago",
        "job_description": "Talent is seeking a Technical Lead to join our client, a large commercial client.",
        "job_title": "Technical Lead | Data",
        "job_url": "https://www.seek.com.au/job/73020146?type=standout&ref=search-standalone",
        "location": "Melbourne VIC",
        "salary": null
    },
    {
        "additional_info": "",
        "company_name": "Airlock Digital Pty Ltd",
        "is_new": true,
        "job_date": "6h ago",
        "job_description": "We are seeking a proficient Golang engineer to take ownership over key domains within our codebase and work with a high level of autonomy.",
        "job_title": "Software Developer - Remote",
        "job_url": "https://www.seek.com.au/job/73019962?type=standout&ref=search-standalone",
        "location": "Adelaide SA",
        "salary": null
    },
    {
        "additional_info": "",
        "company_name": "aXcelerate",
        "is_new": true,
        "job_date": "6h ago",
        "job_description": "Join a highly efficient Development Team! If you are keen to make a difference in the field of education and training then do not hesitate to apply!",
        "job_title": "Senior Software Developer",
        "job_url": "https://www.seek.com.au/job/73019943?type=standout&ref=search-standalone",
        "location": "Brisbane QLD",
        "salary": null
    },
    {
        "additional_info": "",
        "company_name": "Deloitte",
        "is_new": true,
        "job_date": "6h ago",
        "job_description": "The Data Engineer will be a key member of our team. This role involves constructing robust and scalable data pipelines, exploring and implementing ...",
        "job_title": "Data Engineer | Generative AI",
        "job_url": "https://www.seek.com.au/job/73023392?type=standard&ref=search-standalone",
        "location": "Sydney NSW",
        "salary": null
    },
    {
        "additional_info": "",
        "company_name": "face2face Recruitment",
        "is_new": true,
        "job_date": "6h ago",
        "job_description": "You will be in responsible for software design and development using Java, Oracle technologies, and JavaScript.",
        "job_title": "Java Software Developer",
        "job_url": "https://www.seek.com.au/job/73019862?type=standout&ref=search-standalone",
        "location": "Sydney NSW",
        "salary": null
    },
    {
        "additional_info": "",
        "company_name": "Morgan Consulting",
        "is_new": true,
        "job_date": "6h ago",
        "job_description": "Ruby on Rails Developer | Melbourne office based 3 days per week in the office | $65K-$150K + super | Permanent Role | 3 yrs Ruby MINIMUM |",
        "job_title": "Ruby on Rails Developer",
        "job_url": "https://www.seek.com.au/job/73019854?type=standard&ref=search-standalone",
        "location": "Melbourne VIC",
        "salary": "$65K-$150K + super Maximum salary"
    },
    {
        "additional_info": "",
        "company_name": "Unseen Intelligence Pty Ltd",
        "is_new": true,
        "job_date": "6h ago",
        "job_description": "As the Director of Technology, you will direct our technology team in the development and optimization of our AI-powered data science platforms.",
        "job_title": "Director of Technology",
        "job_url": "https://www.seek.com.au/job/73018988?type=standard&ref=search-standalone",
        "location": "Sydney NSW",
        "salary": "$111,000 per year"
    },
    {
        "additional_info": "",
        "company_name": "Randstad Digital",
        "is_new": true,
        "job_date": "6h ago",
        "job_description": "Azure Integration - Financial Services Industry - Fantastic Work Culture - Hybrid Flex - Melbourne CBD",
        "job_title": "Azure Integration Developer",
        "job_url": "https://www.seek.com.au/job/73019453?type=standard&ref=search-standalone",
        "location": "Melbourne VIC",
        "salary": "flexibility, hybrid 2-3 days, great culture"
    },
    {
        "additional_info": "",
        "company_name": "McKay Drilling",
        "is_new": true,
        "job_date": "6h ago",
        "job_description": "Develop a cutting-edge Drill Data Hub and Analytics Output System, bringing data to life with Angular brilliance.",
        "job_title": "Web Developer",
        "job_url": "https://www.seek.com.au/job/73019387?type=standout&ref=search-standalone",
        "location": "Wangara",
        "salary": null
    },
    {
        "additional_info": "",
        "company_name": "Bitplex",
        "is_new": true,
        "job_date": null,
        "job_description": "We have an opportunity in our team for a Full Stack Angular, located on the beautiful Sunshine Coast.",
        "job_title": "Mid-Level Full Stack Developer - Custom Software Solutions",
        "job_url": "https://www.seek.com.au/job/72847817?type=promoted&ref=search-standalone",
        "location": "Chevallum",
        "salary": null
    },
    {
        "additional_info": "",
        "company_name": "Genesis Recruitment Solutions",
        "is_new": true,
        "job_date": null,
        "job_description": "The Senior DevOps Engineer will be responsible for the deployment and upgrade of SaaS products on to AWS cloud, and ensure seamless operations.",
        "job_title": "Senior DevOps Engineer - AWS | Ansible | Terraform",
        "job_url": "https://www.seek.com.au/job/73009456?type=promoted&ref=search-standalone",
        "location": "Melbourne VIC",
        "salary": "$1000-$1100 per Day"
    },
    {
        "additional_info": "",
        "company_name": "Clarrow Pty Ltd",
        "is_new": true,
        "job_date": "6h ago",
        "job_description": "Are you an ambitious Quant Engineer who has a background in C++ / Python and Quant Strategies?",
        "job_title": "Quantitative Python Developer Capital Markets Quant Desk",
        "job_url": "https://www.seek.com.au/job/73019242?type=standard&ref=search-standalone",
        "location": "Melbourne VIC",
        "salary": null
    },
    {
        "additional_info": "",
        "company_name": "Preacta Recruitment",
        "is_new": true,
        "job_date": "6h ago",
        "job_description": "Preacta are currently looking for a Mid - Senior level Site Reliability Engineer or a DevOps Engineer with SRE experience.",
        "job_title": "Site Reliability Engineer",
        "job_url": "https://www.seek.com.au/job/73019127?type=standout&ref=search-standalone",
        "location": "Melbourne VIC",
        "salary": null
    },
    {
        "additional_info": "",
        "company_name": "Citra Solutions",
        "is_new": true,
        "job_date": "6h ago",
        "job_description": "A dynamic startup consultancy is currently seeking an AWS/Node.js/React Developer with a proven track record to join their team on a permanent basis.",
        "job_title": "AWS/Node.js/React Developer",
        "job_url": "https://www.seek.com.au/job/73018803?type=standard&ref=search-standalone",
        "location": "North Sydney",
        "salary": null
    },
    {
        "additional_info": "",
        "company_name": "Peoplebank Australia VIC",
        "is_new": true,
        "job_date": "6h ago",
        "job_description": "Part of the Cloud Platform Engineering function working as part of a team that is responsible for development of cloud platform products.",
        "job_title": "Cloud Engineer",
        "job_url": "https://www.seek.com.au/job/73018169?type=standout&ref=search-standalone",
        "location": "Melbourne VIC",
        "salary": null
    },
    {
        "additional_info": "",
        "company_name": "The Onset",
        "is_new": true,
        "job_date": "6h ago",
        "job_description": "Join health tech business to shape the future of healthcare technology, improve patient care, and be part of a dynamic team dedicated to innovation.",
        "job_title": "Lead DevOps Engineer",
        "job_url": "https://www.seek.com.au/job/73017862?type=standout&ref=search-standalone",
        "location": "Sydney NSW",
        "salary": "$180,000 - $200,000 + Super"
    },
    {
        "additional_info": "",
        "company_name": "Sinorbis Australia Pty Ltd",
        "is_new": true,
        "job_date": "6h ago",
        "job_description": "This is your chance to work for an innovative leading technology startup, offering businesses the access to the world\u2019s\u00a0largest\u00a0online market.",
        "job_title": "Senior Frontend Engineer",
        "job_url": "https://www.seek.com.au/job/73017772?type=standard&ref=search-standalone",
        "location": "Sydney NSW",
        "salary": null
    },
    {
        "additional_info": "",
        "company_name": "Davidson",
        "is_new": true,
        "job_date": "6h ago",
        "job_description": "Java Developer Contract until 31st December 2024, Support system upgrade, hybrid working, excellent rates, Possible extension.",
        "job_title": "Java Developer",
        "job_url": "https://www.seek.com.au/job/73017643?type=standard&ref=search-standalone",
        "location": "North Lakes",
        "salary": null
    },
    {
        "additional_info": "",
        "company_name": "Latitude IT",
        "is_new": true,
        "job_date": "7h ago",
        "job_description": "We have a new long-term contract opportunity available for a Salesforce Develop who brings hands-on experience with OmniScript",
        "job_title": "Salesforce Developer - OmniScript experience required",
        "job_url": "https://www.seek.com.au/job/73016915?type=standard&ref=search-standalone",
        "location": "Melbourne VIC",
        "salary": "Contract rate open to negotiation"
    },
    {
        "additional_info": "",
        "company_name": "The Onset",
        "is_new": true,
        "job_date": "7h ago",
        "job_description": "You could wake up knowing that you're building software that helps guide young people on a path towards meaningful careers after school.",
        "job_title": "Full Stack PHP Developer",
        "job_url": "https://www.seek.com.au/job/73016715?type=standout&ref=search-standalone",
        "location": "Sydney NSW",
        "salary": "Up to $160K + Super"
    },
    {
        "additional_info": "",
        "company_name": "Australian Council for Educational Research (ACER)",
        "is_new": true,
        "job_date": "7h ago",
        "job_description": "Provide a web-based platform to deliver ACER's assessment services to our customers and students globally.",
        "job_title": "Software Engineer (Level 2)",
        "job_url": "https://www.seek.com.au/job/73016471?type=standout&ref=search-standalone",
        "location": "Camberwell",
        "salary": "$102,719 - $113,534 plus 17% super"
    },
    {
        "additional_info": "",
        "company_name": "Latitude IT",
        "is_new": true,
        "job_date": "7h ago",
        "job_description": "We have a new long-term contract opportunity available for a Salesforce Develop who brings hands-on experience with OmniScript",
        "job_title": "Salesforce Developer - OmniScript experience required",
        "job_url": "https://www.seek.com.au/job/73016446?type=standard&ref=search-standalone",
        "location": "Adelaide SA",
        "salary": "Contract rate open to negotiation"
    },
    {
        "additional_info": "",
        "company_name": "The Onset",
        "is_new": true,
        "job_date": "7h ago",
        "job_description": "Want stability in a new role but also building brand-new stuff in a start-up environment?",
        "job_title": "Senior JavaScript Engineer",
        "job_url": "https://www.seek.com.au/job/73016254?type=standout&ref=search-standalone",
        "location": "Sydney NSW",
        "salary": "AUD 120000 - 150000 per annum, + super"
    },
    {
        "additional_info": "",
        "company_name": "The Onset",
        "is_new": true,
        "job_date": "7h ago",
        "job_description": "A product built by developers, for developers - if you have an idea of how tech can be used differently, you have the freedom do it.",
        "job_title": "Senior Full-stack Engineer",
        "job_url": "https://www.seek.com.au/job/73016091?type=standout&ref=search-standalone",
        "location": "Sydney NSW",
        "salary": "$180k + super + equity"
    },
    {
        "additional_info": "",
        "company_name": "DWS Limited",
        "is_new": true,
        "job_date": "7h ago",
        "job_description": "Australian Citizenship w/current Baseline is ESSENTIAL. Proven experience designing and using Microsoft IIS is VITAL. Exciting work w/ tier 1 clients",
        "job_title": "Microsoft IIS Designer / Engineer - Australian Citizen",
        "job_url": "https://www.seek.com.au/job/73016055?type=standout&ref=search-standalone",
        "location": "Canberra ACT",
        "salary": "up to $180K package (inc super) dep. on exp."
    },
    {
        "additional_info": "",
        "company_name": "Davidson",
        "is_new": true,
        "job_date": "7h ago",
        "job_description": "Full-Stack Developer with C#/ASP.Net and React strengths required to join this fun and energetic development team. Senior and Lead positions available",
        "job_title": "Full Stack Developer",
        "job_url": "https://www.seek.com.au/job/73016040?type=standard&ref=search-standalone",
        "location": "Brisbane QLD",
        "salary": "$130k - $150k p.a. + Super"
    },
    {
        "additional_info": "",
        "company_name": "Paxus",
        "is_new": true,
        "job_date": "7h ago",
        "job_description": "We are seeking talented and passionate Java Developers to join our dynamic IT team.",
        "job_title": "Seven (7) Java Developers",
        "job_url": "https://www.seek.com.au/job/73016021?type=standout&ref=search-standalone",
        "location": "North Lakes",
        "salary": null
    },
    {
        "additional_info": "",
        "company_name": "SALT SEARCH PTY LTD",
        "is_new": true,
        "job_date": "7h ago",
        "job_description": "Exciting opportunity for a Software Engineer to join a leading Australian brand, where you'll be working across a high profile transformation project.",
        "job_title": "Software Engineer",
        "job_url": "https://www.seek.com.au/job/73015699?type=standout&ref=search-standalone",
        "location": "Melbourne VIC",
        "salary": "$120k - $135k p.a. + Bonus"
    },
    {
        "additional_info": "",
        "company_name": "Austcorp Executive",
        "is_new": true,
        "job_date": "7h ago",
        "job_description": "A Principal Engineer required to be part of a high growth start up and take ownership across engineering. Equity on offer after 6 month probation.",
        "job_title": "Principal Engineer - High Growth Start up - Fully remote - $200k-$250k+ Super",
        "job_url": "https://www.seek.com.au/job/73015673?type=standout&ref=search-standalone",
        "location": "Sydney NSW",
        "salary": null
    },
    {
        "additional_info": "",
        "company_name": "Davidson",
        "is_new": true,
        "job_date": "7h ago",
        "job_description": "Senior PM required to set up a new IT domain as part of a new joint venture/allaince.  Strong vendor skillset required - 12 month contract",
        "job_title": "Senior Project Manager",
        "job_url": "https://www.seek.com.au/job/73015507?type=standard&ref=search-standalone",
        "location": "Brisbane QLD",
        "salary": "$1k - $1200 p.d. + Super"
    },
    {
        "additional_info": "",
        "company_name": "Bluefin Resources Pty Limited",
        "is_new": true,
        "job_date": "7h ago",
        "job_description": "Senior Full Stack .NET + Azure Engineer\nHybrid Working Environment",
        "job_title": "Melbourne -  Senior Azure Integration Developer",
        "job_url": "https://www.seek.com.au/job/73015455?type=standard&ref=search-standalone",
        "location": "Melbourne VIC",
        "salary": "$1500000.00 - $1700000.00 p.a."
    }
]